ingot_sql/__init__.py
ingot_sql/bootstrap/__init__.py
ingot_sql/bootstrap/base.py
ingot_sql/bootstrap/scaffolding/__init__.py
ingot_sql/scripts/__init__.py
ingot_sql/scripts/ingot_sql.py
ingot_sql/tests/__init__.py
ingot_sql/tests/functionals/__init__.py
ingot_sql/tests/units/__init__.py
ingot_sql/tests/units/bootstrap/__init__.py
ingot_sql/tests/units/bootstrap/test_base.py
ingot_sql/tests/units/scripts/__init__.py
ingot_sql/tests/units/scripts/test_ingot_sql.py
ingot_sql-0.1.0.dist-info/LICENSE
ingot_sql-0.1.0.dist-info/METADATA
ingot_sql-0.1.0.dist-info/WHEEL
ingot_sql-0.1.0.dist-info/entry_points.txt
ingot_sql-0.1.0.dist-info/top_level.txt
ingot_sql-0.1.0.dist-info/RECORD
